MANIFEST.in
README.rst
setup.py
dj_facebook_realtime/__init__.py
dj_facebook_realtime/models.py
dj_facebook_realtime/settings.py
dj_facebook_realtime/signals.py
dj_facebook_realtime/urls.py
dj_facebook_realtime/utils.py
dj_facebook_realtime/views.py
dj_facebook_realtime/management/__init__.py
dj_facebook_realtime/management/commands/__init__.py
dj_facebook_realtime/management/commands/realtime_subscriptions_add.py
dj_facebook_realtime/management/commands/realtime_subscriptions_delete.py
dj_facebook_realtime/management/commands/realtime_subscriptions_list.py
dj_facebook_realtime/tests/__init__.py
dj_facebook_realtime/tests/test_views.py
django_facebook_realtime.egg-info/PKG-INFO
django_facebook_realtime.egg-info/SOURCES.txt
django_facebook_realtime.egg-info/dependency_links.txt
django_facebook_realtime.egg-info/requires.txt
django_facebook_realtime.egg-info/top_level.txt