Metadata-Version: 1.1
Name: django-facebook-realtime
Version: 0.1.1-20130208
Summary: django app for adding/removing/listing facebook realtime subscriptions and retrieving facebook realtime updates
Home-page: https://github.com/rmaceissoft/django-facebook-realtime
Author: Reiner Marquez
Author-email: rmaceissoft@gmail.com
License: UNKNOWN
Platform: UNKNOWN
Classifier: Development Status :: 4 - Beta
Classifier: Framework :: Django
Classifier: Intended Audience :: Developers
Classifier: Intended Audience :: Information Technology
Classifier: License :: OSI Approved :: BSD License
Classifier: Operating System :: OS Independent
Classifier: Programming Language :: Python
